linksopen/__init__.py
linksopen/main.py
linksopen-0.1.4.dist-info/licenses/LICENSE
linksopen-0.1.4.dist-info/METADATA
linksopen-0.1.4.dist-info/WHEEL
linksopen-0.1.4.dist-info/entry_points.txt
linksopen-0.1.4.dist-info/top_level.txt
linksopen-0.1.4.dist-info/RECORD
