Metadata-Version: 2.4
Name: linksopen
Version: 0.1.4
Summary: Handle gracefully openning links that are inside text files. Simple as that.
Author-email: Rodolfo Franca <souzafrodolfo@gmail.com>
License: MIT
Project-URL: Homepage, https://github.com/rodhfr/linksopen
Classifier: Programming Language :: Python :: 3
Classifier: License :: OSI Approved :: MIT License
Classifier: Development Status :: 4 - Beta
Classifier: Intended Audience :: Developers
Requires-Python: >=3.14
License-File: LICENSE
Requires-Dist: build>=1.4.0
Requires-Dist: pip>=25.3
Requires-Dist: setuptools>=80.9.0
Requires-Dist: twine>=6.2.0
Requires-Dist: wheel>=0.45.1
Dynamic: license-file
